{
    "Name": "Bella Beer",

  "Dialogue": [
    "Hey! Jij hebt echt al best veel volgers.",
    "Dan is het tijd om wat terug te doen voor anderen door 50 munten te geven aan een goed doel..",
    "Misschien bedenk je je nog!",
    "Dankjewel! Iets leuks doen voor anderen voelt goed om te doen!"

  ],

  "PlayerDialogue": [
    "Ja he, vind ik ook.",
    "Pff, nee dat is mijn eigen geld dat ik zelf heb gespaard!",
    "Goed idee! Zijn ze vast blij mee!"
  ],

    "NewDialogueFile": "BellaBeer2",
    "WhenToShowNewDialogue": -1,
    "ChoosingDialogue": "quest",
    "ToBeReplaced": [
        ]
}
